mkdocs_caseinsensitive_plugin/__init__.py
mkdocs_caseinsensitive_plugin/plugin.py
mkdocs_caseinsensitive_plugin-0.4.1.dist-info/entry_points.txt
mkdocs_caseinsensitive_plugin-0.4.1.dist-info/LICENSE
mkdocs_caseinsensitive_plugin-0.4.1.dist-info/WHEEL
mkdocs_caseinsensitive_plugin-0.4.1.dist-info/METADATA
mkdocs_caseinsensitive_plugin-0.4.1.dist-info/RECORD
