Metadata-Version: 2.1
Name: mkdocs-caseinsensitive-plugin
Version: 0.4.1
Summary: 
License: AGPL V3
Author: TheMythologist
Author-email: leekaixuan2001@gmail.com
Requires-Python: >=3.10,<4.0
Classifier: License :: Other/Proprietary License
Classifier: Programming Language :: Python :: 3
Classifier: Programming Language :: Python :: 3.10
Classifier: Programming Language :: Python :: 3.11
Requires-Dist: mkdocs (>=1.4.2,<2.0.0)
Requires-Dist: regex (>=2022.10.31,<2023.0.0)
